pylinkirc/README.md
pylinkirc/VERSION
pylinkirc/__init__.py
pylinkirc/classes.py
pylinkirc/conf.py
pylinkirc/example-conf.yml
pylinkirc/launcher.py
pylinkirc/log.py
pylinkirc/selectdriver.py
pylinkirc/structures.py
pylinkirc/utils.py
pylinkirc/world.py
pylinkirc/coremods/__init__.py
pylinkirc/coremods/control.py
pylinkirc/coremods/corecommands.py
pylinkirc/coremods/exttargets.py
pylinkirc/coremods/handlers.py
pylinkirc/coremods/login.py
pylinkirc/coremods/permissions.py
pylinkirc/coremods/service_support.py
pylinkirc/plugins/__init__.py
pylinkirc/plugins/antispam.py
pylinkirc/plugins/automode.py
pylinkirc/plugins/bots.py
pylinkirc/plugins/changehost.py
pylinkirc/plugins/commands.py
pylinkirc/plugins/ctcp.py
pylinkirc/plugins/example.py
pylinkirc/plugins/exec.py
pylinkirc/plugins/fantasy.py
pylinkirc/plugins/games.py
pylinkirc/plugins/global.py
pylinkirc/plugins/networks.py
pylinkirc/plugins/opercmds.py
pylinkirc/plugins/raw.py
pylinkirc/plugins/relay.py
pylinkirc/plugins/relay_clientbot.py
pylinkirc/plugins/servermaps.py
pylinkirc/plugins/servprotect.py
pylinkirc/plugins/stats.py
pylinkirc/protocols/__init__.py
pylinkirc/protocols/clientbot.py
pylinkirc/protocols/hybrid.py
pylinkirc/protocols/inspircd.py
pylinkirc/protocols/ircs2s_common.py
pylinkirc/protocols/nefarious.py
pylinkirc/protocols/ngircd.py
pylinkirc/protocols/p10.py
pylinkirc/protocols/ts6.py
pylinkirc/protocols/ts6_common.py
pylinkirc/protocols/unreal.py
pylinkirc-2.0.0.data/scripts/pylink-mkpasswd
pylinkirc-2.0.0.dist-info/DESCRIPTION.rst
pylinkirc-2.0.0.dist-info/METADATA
pylinkirc-2.0.0.dist-info/RECORD
pylinkirc-2.0.0.dist-info/WHEEL
pylinkirc-2.0.0.dist-info/dependency_links.txt
pylinkirc-2.0.0.dist-info/entry_points.txt
pylinkirc-2.0.0.dist-info/metadata.json
pylinkirc-2.0.0.dist-info/top_level.txt
