Metadata-Version: 2.0
Name: pylinkirc
Version: 2.0.0
Summary: PyLink IRC Services
Home-page: https://github.com/jlu5/PyLink
Author: James Lu
Author-email: james@overdrivenetworks.com
License: MPL 2.0
Keywords: IRC services relay
Platform: UNKNOWN
Classifier: Development Status :: 5 - Production/Stable
Classifier: Intended Audience :: Developers
Classifier: Intended Audience :: System Administrators
Classifier: Topic :: Communications :: Chat :: Internet Relay Chat
Classifier: Topic :: Software Development :: Libraries :: Python Modules
Classifier: License :: OSI Approved :: Mozilla Public License 2.0 (MPL 2.0)
Classifier: Environment :: Console
Classifier: Operating System :: OS Independent
Classifier: Operating System :: POSIX
Classifier: Natural Language :: English
Classifier: Programming Language :: Python :: 3 :: Only
Classifier: Programming Language :: Python :: 3.4
Classifier: Programming Language :: Python :: 3.5
Classifier: Programming Language :: Python :: 3.6
Provides-Extra: cron-support
Provides-Extra: password-hashing
Provides-Extra: servprotect
Requires-Dist: ircmatch
Requires-Dist: pyyaml
Provides-Extra: cron-support
Requires-Dist: psutil; extra == 'cron-support'
Provides-Extra: password-hashing
Requires-Dist: passlib; extra == 'password-hashing'
Provides-Extra: servprotect
Requires-Dist: expiringdict (>=1.1.4); extra == 'servprotect'
